{"nodes": [{"id": "c_users_useras_desktop_where_where_android_kiro_specs_chat_ui_redesign_requirements_md", "label": "requirements.md", "file_type": "document", "source_file": "C:\\Users\\USERAS\\Desktop\\where\\where-android\\.kiro\\specs\\chat-ui-redesign\\requirements.md", "source_location": "L1"}, {"id": "chat_ui_redesign_requirements_requirements_document", "label": "Requirements Document", "file_type": "document", "source_file": "C:\\Users\\USERAS\\Desktop\\where\\where-android\\.kiro\\specs\\chat-ui-redesign\\requirements.md", "source_location": "L1"}, {"id": "chat_ui_redesign_requirements_introduction", "label": "Introduction", "file_type": "document", "source_file": "C:\\Users\\USERAS\\Desktop\\where\\where-android\\.kiro\\specs\\chat-ui-redesign\\requirements.md", "source_location": "L3"}, {"id": "chat_ui_redesign_requirements_glossary", "label": "Glossary", "file_type": "document", "source_file": "C:\\Users\\USERAS\\Desktop\\where\\where-android\\.kiro\\specs\\chat-ui-redesign\\requirements.md", "source_location": "L7"}, {"id": "chat_ui_redesign_requirements_requirements", "label": "Requirements", "file_type": "document", "source_file": "C:\\Users\\USERAS\\Desktop\\where\\where-android\\.kiro\\specs\\chat-ui-redesign\\requirements.md", "source_location": "L25"}, {"id": "chat_ui_redesign_requirements_requirement_1_username_display_fix_in_conversation_list", "label": "Requirement 1: Username Display Fix in Conversation List", "file_type": "document", "source_file": "C:\\Users\\USERAS\\Desktop\\where\\where-android\\.kiro\\specs\\chat-ui-redesign\\requirements.md", "source_location": "L27"}, {"id": "chat_ui_redesign_requirements_acceptance_criteria", "label": "Acceptance Criteria", "file_type": "document", "source_file": "C:\\Users\\USERAS\\Desktop\\where\\where-android\\.kiro\\specs\\chat-ui-redesign\\requirements.md", "source_location": "L31"}, {"id": "chat_ui_redesign_requirements_requirement_2_username_display_fix_in_chat_screen", "label": "Requirement 2: Username Display Fix in Chat Screen", "file_type": "document", "source_file": "C:\\Users\\USERAS\\Desktop\\where\\where-android\\.kiro\\specs\\chat-ui-redesign\\requirements.md", "source_location": "L38"}, {"id": "chat_ui_redesign_requirements_acceptance_criteria_42", "label": "Acceptance Criteria", "file_type": "document", "source_file": "C:\\Users\\USERAS\\Desktop\\where\\where-android\\.kiro\\specs\\chat-ui-redesign\\requirements.md", "source_location": "L42"}, {"id": "chat_ui_redesign_requirements_requirement_3_messenger_style_conversation_list_design", "label": "Requirement 3: Messenger-Style Conversation List Design", "file_type": "document", "source_file": "C:\\Users\\USERAS\\Desktop\\where\\where-android\\.kiro\\specs\\chat-ui-redesign\\requirements.md", "source_location": "L50"}, {"id": "chat_ui_redesign_requirements_acceptance_criteria_54", "label": "Acceptance Criteria", "file_type": "document", "source_file": "C:\\Users\\USERAS\\Desktop\\where\\where-android\\.kiro\\specs\\chat-ui-redesign\\requirements.md", "source_location": "L54"}, {"id": "chat_ui_redesign_requirements_requirement_4_messenger_style_chat_bubble_design", "label": "Requirement 4: Messenger-Style Chat Bubble Design", "file_type": "document", "source_file": "C:\\Users\\USERAS\\Desktop\\where\\where-android\\.kiro\\specs\\chat-ui-redesign\\requirements.md", "source_location": "L68"}, {"id": "chat_ui_redesign_requirements_acceptance_criteria_72", "label": "Acceptance Criteria", "file_type": "document", "source_file": "C:\\Users\\USERAS\\Desktop\\where\\where-android\\.kiro\\specs\\chat-ui-redesign\\requirements.md", "source_location": "L72"}, {"id": "chat_ui_redesign_requirements_requirement_5_professional_input_bar_design", "label": "Requirement 5: Professional Input Bar Design", "file_type": "document", "source_file": "C:\\Users\\USERAS\\Desktop\\where\\where-android\\.kiro\\specs\\chat-ui-redesign\\requirements.md", "source_location": "L84"}, {"id": "chat_ui_redesign_requirements_acceptance_criteria_88", "label": "Acceptance Criteria", "file_type": "document", "source_file": "C:\\Users\\USERAS\\Desktop\\where\\where-android\\.kiro\\specs\\chat-ui-redesign\\requirements.md", "source_location": "L88"}, {"id": "chat_ui_redesign_requirements_requirement_6_chat_header_redesign", "label": "Requirement 6: Chat Header Redesign", "file_type": "document", "source_file": "C:\\Users\\USERAS\\Desktop\\where\\where-android\\.kiro\\specs\\chat-ui-redesign\\requirements.md", "source_location": "L97"}, {"id": "chat_ui_redesign_requirements_acceptance_criteria_101", "label": "Acceptance Criteria", "file_type": "document", "source_file": "C:\\Users\\USERAS\\Desktop\\where\\where-android\\.kiro\\specs\\chat-ui-redesign\\requirements.md", "source_location": "L101"}, {"id": "chat_ui_redesign_requirements_requirement_7_messenger_style_chat_screen_top_bar", "label": "Requirement 7: Messenger-Style Chat Screen Top Bar", "file_type": "document", "source_file": "C:\\Users\\USERAS\\Desktop\\where\\where-android\\.kiro\\specs\\chat-ui-redesign\\requirements.md", "source_location": "L111"}, {"id": "chat_ui_redesign_requirements_acceptance_criteria_115", "label": "Acceptance Criteria", "file_type": "document", "source_file": "C:\\Users\\USERAS\\Desktop\\where\\where-android\\.kiro\\specs\\chat-ui-redesign\\requirements.md", "source_location": "L115"}, {"id": "chat_ui_redesign_requirements_requirement_8_messenger_style_conversation_info_screen", "label": "Requirement 8: Messenger-Style Conversation Info Screen", "file_type": "document", "source_file": "C:\\Users\\USERAS\\Desktop\\where\\where-android\\.kiro\\specs\\chat-ui-redesign\\requirements.md", "source_location": "L129"}, {"id": "chat_ui_redesign_requirements_acceptance_criteria_133", "label": "Acceptance Criteria", "file_type": "document", "source_file": "C:\\Users\\USERAS\\Desktop\\where\\where-android\\.kiro\\specs\\chat-ui-redesign\\requirements.md", "source_location": "L133"}, {"id": "chat_ui_redesign_requirements_requirement_9_messenger_style_group_info_and_management", "label": "Requirement 9: Messenger-Style Group Info and Management", "file_type": "document", "source_file": "C:\\Users\\USERAS\\Desktop\\where\\where-android\\.kiro\\specs\\chat-ui-redesign\\requirements.md", "source_location": "L144"}, {"id": "chat_ui_redesign_requirements_acceptance_criteria_148", "label": "Acceptance Criteria", "file_type": "document", "source_file": "C:\\Users\\USERAS\\Desktop\\where\\where-android\\.kiro\\specs\\chat-ui-redesign\\requirements.md", "source_location": "L148"}, {"id": "chat_ui_redesign_requirements_requirement_10_visual_polish_and_consistency", "label": "Requirement 10: Visual Polish and Consistency", "file_type": "document", "source_file": "C:\\Users\\USERAS\\Desktop\\where\\where-android\\.kiro\\specs\\chat-ui-redesign\\requirements.md", "source_location": "L162"}, {"id": "chat_ui_redesign_requirements_acceptance_criteria_166", "label": "Acceptance Criteria", "file_type": "document", "source_file": "C:\\Users\\USERAS\\Desktop\\where\\where-android\\.kiro\\specs\\chat-ui-redesign\\requirements.md", "source_location": "L166"}], "edges": [{"source": "c_users_useras_desktop_where_where_android_kiro_specs_chat_ui_redesign_requirements_md", "target": "chat_ui_redesign_requirements_requirements_document", "relation": "contains", "confidence": "EXTRACTED", "source_file": "C:\\Users\\USERAS\\Desktop\\where\\where-android\\.kiro\\specs\\chat-ui-redesign\\requirements.md", "source_location": "L1", "weight": 1.0}, {"source": "chat_ui_redesign_requirements_requirements_document", "target": "chat_ui_redesign_requirements_introduction", "relation": "contains", "confidence": "EXTRACTED", "source_file": "C:\\Users\\USERAS\\Desktop\\where\\where-android\\.kiro\\specs\\chat-ui-redesign\\requirements.md", "source_location": "L3", "weight": 1.0}, {"source": "chat_ui_redesign_requirements_requirements_document", "target": "chat_ui_redesign_requirements_glossary", "relation": "contains", "confidence": "EXTRACTED", "source_file": "C:\\Users\\USERAS\\Desktop\\where\\where-android\\.kiro\\specs\\chat-ui-redesign\\requirements.md", "source_location": "L7", "weight": 1.0}, {"source": "chat_ui_redesign_requirements_requirements_document", "target": "chat_ui_redesign_requirements_requirements", "relation": "contains", "confidence": "EXTRACTED", "source_file": "C:\\Users\\USERAS\\Desktop\\where\\where-android\\.kiro\\specs\\chat-ui-redesign\\requirements.md", "source_location": "L25", "weight": 1.0}, {"source": "chat_ui_redesign_requirements_requirements", "target": "chat_ui_redesign_requirements_requirement_1_username_display_fix_in_conversation_list", "relation": "contains", "confidence": "EXTRACTED", "source_file": "C:\\Users\\USERAS\\Desktop\\where\\where-android\\.kiro\\specs\\chat-ui-redesign\\requirements.md", "source_location": "L27", "weight": 1.0}, {"source": "chat_ui_redesign_requirements_requirement_1_username_display_fix_in_conversation_list", "target": "chat_ui_redesign_requirements_acceptance_criteria", "relation": "contains", "confidence": "EXTRACTED", "source_file": "C:\\Users\\USERAS\\Desktop\\where\\where-android\\.kiro\\specs\\chat-ui-redesign\\requirements.md", "source_location": "L31", "weight": 1.0}, {"source": "chat_ui_redesign_requirements_requirements", "target": "chat_ui_redesign_requirements_requirement_2_username_display_fix_in_chat_screen", "relation": "contains", "confidence": "EXTRACTED", "source_file": "C:\\Users\\USERAS\\Desktop\\where\\where-android\\.kiro\\specs\\chat-ui-redesign\\requirements.md", "source_location": "L38", "weight": 1.0}, {"source": "chat_ui_redesign_requirements_requirement_2_username_display_fix_in_chat_screen", "target": "chat_ui_redesign_requirements_acceptance_criteria_42", "relation": "contains", "confidence": "EXTRACTED", "source_file": "C:\\Users\\USERAS\\Desktop\\where\\where-android\\.kiro\\specs\\chat-ui-redesign\\requirements.md", "source_location": "L42", "weight": 1.0}, {"source": "chat_ui_redesign_requirements_requirements", "target": "chat_ui_redesign_requirements_requirement_3_messenger_style_conversation_list_design", "relation": "contains", "confidence": "EXTRACTED", "source_file": "C:\\Users\\USERAS\\Desktop\\where\\where-android\\.kiro\\specs\\chat-ui-redesign\\requirements.md", "source_location": "L50", "weight": 1.0}, {"source": "chat_ui_redesign_requirements_requirement_3_messenger_style_conversation_list_design", "target": "chat_ui_redesign_requirements_acceptance_criteria_54", "relation": "contains", "confidence": "EXTRACTED", "source_file": "C:\\Users\\USERAS\\Desktop\\where\\where-android\\.kiro\\specs\\chat-ui-redesign\\requirements.md", "source_location": "L54", "weight": 1.0}, {"source": "chat_ui_redesign_requirements_requirements", "target": "chat_ui_redesign_requirements_requirement_4_messenger_style_chat_bubble_design", "relation": "contains", "confidence": "EXTRACTED", "source_file": "C:\\Users\\USERAS\\Desktop\\where\\where-android\\.kiro\\specs\\chat-ui-redesign\\requirements.md", "source_location": "L68", "weight": 1.0}, {"source": "chat_ui_redesign_requirements_requirement_4_messenger_style_chat_bubble_design", "target": "chat_ui_redesign_requirements_acceptance_criteria_72", "relation": "contains", "confidence": "EXTRACTED", "source_file": "C:\\Users\\USERAS\\Desktop\\where\\where-android\\.kiro\\specs\\chat-ui-redesign\\requirements.md", "source_location": "L72", "weight": 1.0}, {"source": "chat_ui_redesign_requirements_requirements", "target": "chat_ui_redesign_requirements_requirement_5_professional_input_bar_design", "relation": "contains", "confidence": "EXTRACTED", "source_file": "C:\\Users\\USERAS\\Desktop\\where\\where-android\\.kiro\\specs\\chat-ui-redesign\\requirements.md", "source_location": "L84", "weight": 1.0}, {"source": "chat_ui_redesign_requirements_requirement_5_professional_input_bar_design", "target": "chat_ui_redesign_requirements_acceptance_criteria_88", "relation": "contains", "confidence": "EXTRACTED", "source_file": "C:\\Users\\USERAS\\Desktop\\where\\where-android\\.kiro\\specs\\chat-ui-redesign\\requirements.md", "source_location": "L88", "weight": 1.0}, {"source": "chat_ui_redesign_requirements_requirements", "target": "chat_ui_redesign_requirements_requirement_6_chat_header_redesign", "relation": "contains", "confidence": "EXTRACTED", "source_file": "C:\\Users\\USERAS\\Desktop\\where\\where-android\\.kiro\\specs\\chat-ui-redesign\\requirements.md", "source_location": "L97", "weight": 1.0}, {"source": "chat_ui_redesign_requirements_requirement_6_chat_header_redesign", "target": "chat_ui_redesign_requirements_acceptance_criteria_101", "relation": "contains", "confidence": "EXTRACTED", "source_file": "C:\\Users\\USERAS\\Desktop\\where\\where-android\\.kiro\\specs\\chat-ui-redesign\\requirements.md", "source_location": "L101", "weight": 1.0}, {"source": "chat_ui_redesign_requirements_requirements", "target": "chat_ui_redesign_requirements_requirement_7_messenger_style_chat_screen_top_bar", "relation": "contains", "confidence": "EXTRACTED", "source_file": "C:\\Users\\USERAS\\Desktop\\where\\where-android\\.kiro\\specs\\chat-ui-redesign\\requirements.md", "source_location": "L111", "weight": 1.0}, {"source": "chat_ui_redesign_requirements_requirement_7_messenger_style_chat_screen_top_bar", "target": "chat_ui_redesign_requirements_acceptance_criteria_115", "relation": "contains", "confidence": "EXTRACTED", "source_file": "C:\\Users\\USERAS\\Desktop\\where\\where-android\\.kiro\\specs\\chat-ui-redesign\\requirements.md", "source_location": "L115", "weight": 1.0}, {"source": "chat_ui_redesign_requirements_requirements", "target": "chat_ui_redesign_requirements_requirement_8_messenger_style_conversation_info_screen", "relation": "contains", "confidence": "EXTRACTED", "source_file": "C:\\Users\\USERAS\\Desktop\\where\\where-android\\.kiro\\specs\\chat-ui-redesign\\requirements.md", "source_location": "L129", "weight": 1.0}, {"source": "chat_ui_redesign_requirements_requirement_8_messenger_style_conversation_info_screen", "target": "chat_ui_redesign_requirements_acceptance_criteria_133", "relation": "contains", "confidence": "EXTRACTED", "source_file": "C:\\Users\\USERAS\\Desktop\\where\\where-android\\.kiro\\specs\\chat-ui-redesign\\requirements.md", "source_location": "L133", "weight": 1.0}, {"source": "chat_ui_redesign_requirements_requirements", "target": "chat_ui_redesign_requirements_requirement_9_messenger_style_group_info_and_management", "relation": "contains", "confidence": "EXTRACTED", "source_file": "C:\\Users\\USERAS\\Desktop\\where\\where-android\\.kiro\\specs\\chat-ui-redesign\\requirements.md", "source_location": "L144", "weight": 1.0}, {"source": "chat_ui_redesign_requirements_requirement_9_messenger_style_group_info_and_management", "target": "chat_ui_redesign_requirements_acceptance_criteria_148", "relation": "contains", "confidence": "EXTRACTED", "source_file": "C:\\Users\\USERAS\\Desktop\\where\\where-android\\.kiro\\specs\\chat-ui-redesign\\requirements.md", "source_location": "L148", "weight": 1.0}, {"source": "chat_ui_redesign_requirements_requirements", "target": "chat_ui_redesign_requirements_requirement_10_visual_polish_and_consistency", "relation": "contains", "confidence": "EXTRACTED", "source_file": "C:\\Users\\USERAS\\Desktop\\where\\where-android\\.kiro\\specs\\chat-ui-redesign\\requirements.md", "source_location": "L162", "weight": 1.0}, {"source": "chat_ui_redesign_requirements_requirement_10_visual_polish_and_consistency", "target": "chat_ui_redesign_requirements_acceptance_criteria_166", "relation": "contains", "confidence": "EXTRACTED", "source_file": "C:\\Users\\USERAS\\Desktop\\where\\where-android\\.kiro\\specs\\chat-ui-redesign\\requirements.md", "source_location": "L166", "weight": 1.0}], "input_tokens": 0, "output_tokens": 0}