{"nodes": [{"id": "c_users_useras_desktop_where_where_android_app_src_main_java_com_ovi_where_di_usecasemodule_kt", "label": "UseCaseModule.kt", "file_type": "code", "source_file": "C:\\Users\\USERAS\\Desktop\\where\\where-android\\app\\src\\main\\java\\com\\ovi\\where\\di\\UseCaseModule.kt", "source_location": "L1"}, {"id": "di_usecasemodule_usecasemodule", "label": "UseCaseModule", "file_type": "code", "source_file": "C:\\Users\\USERAS\\Desktop\\where\\where-android\\app\\src\\main\\java\\com\\ovi\\where\\di\\UseCaseModule.kt", "source_location": "L72"}, {"id": "di_usecasemodule_usecasemodule_providesigninusecase", "label": ".provideSignInUseCase()", "file_type": "code", "source_file": "C:\\Users\\USERAS\\Desktop\\where\\where-android\\app\\src\\main\\java\\com\\ovi\\where\\di\\UseCaseModule.kt", "source_location": "L77"}, {"id": "di_usecasemodule_usecasemodule_provideregisterusecase", "label": ".provideRegisterUseCase()", "file_type": "code", "source_file": "C:\\Users\\USERAS\\Desktop\\where\\where-android\\app\\src\\main\\java\\com\\ovi\\where\\di\\UseCaseModule.kt", "source_location": "L78"}, {"id": "di_usecasemodule_usecasemodule_provideobservecurrentuserusecase", "label": ".provideObserveCurrentUserUseCase()", "file_type": "code", "source_file": "C:\\Users\\USERAS\\Desktop\\where\\where-android\\app\\src\\main\\java\\com\\ovi\\where\\di\\UseCaseModule.kt", "source_location": "L79"}, {"id": "di_usecasemodule_usecasemodule_providesignoutusecase", "label": ".provideSignOutUseCase()", "file_type": "code", "source_file": "C:\\Users\\USERAS\\Desktop\\where\\where-android\\app\\src\\main\\java\\com\\ovi\\where\\di\\UseCaseModule.kt", "source_location": "L80"}, {"id": "di_usecasemodule_usecasemodule_providegooglesigninusecase", "label": ".provideGoogleSignInUseCase()", "file_type": "code", "source_file": "C:\\Users\\USERAS\\Desktop\\where\\where-android\\app\\src\\main\\java\\com\\ovi\\where\\di\\UseCaseModule.kt", "source_location": "L81"}, {"id": "di_usecasemodule_usecasemodule_provideresetpasswordusecase", "label": ".provideResetPasswordUseCase()", "file_type": "code", "source_file": "C:\\Users\\USERAS\\Desktop\\where\\where-android\\app\\src\\main\\java\\com\\ovi\\where\\di\\UseCaseModule.kt", "source_location": "L82"}, {"id": "di_usecasemodule_usecasemodule_provideupdateprofileusecase", "label": ".provideUpdateProfileUseCase()", "file_type": "code", "source_file": "C:\\Users\\USERAS\\Desktop\\where\\where-android\\app\\src\\main\\java\\com\\ovi\\where\\di\\UseCaseModule.kt", "source_location": "L83"}, {"id": "di_usecasemodule_usecasemodule_provideupdatebiousecase", "label": ".provideUpdateBioUseCase()", "file_type": "code", "source_file": "C:\\Users\\USERAS\\Desktop\\where\\where-android\\app\\src\\main\\java\\com\\ovi\\where\\di\\UseCaseModule.kt", "source_location": "L84"}, {"id": "di_usecasemodule_usecasemodule_provideupdateusernameusecase", "label": ".provideUpdateUsernameUseCase()", "file_type": "code", "source_file": "C:\\Users\\USERAS\\Desktop\\where\\where-android\\app\\src\\main\\java\\com\\ovi\\where\\di\\UseCaseModule.kt", "source_location": "L85"}, {"id": "di_usecasemodule_usecasemodule_providecheckusernameavailableusecase", "label": ".provideCheckUsernameAvailableUseCase()", "file_type": "code", "source_file": "C:\\Users\\USERAS\\Desktop\\where\\where-android\\app\\src\\main\\java\\com\\ovi\\where\\di\\UseCaseModule.kt", "source_location": "L86"}, {"id": "di_usecasemodule_usecasemodule_provideupdatehomeusecase", "label": ".provideUpdateHomeUseCase()", "file_type": "code", "source_file": "C:\\Users\\USERAS\\Desktop\\where\\where-android\\app\\src\\main\\java\\com\\ovi\\where\\di\\UseCaseModule.kt", "source_location": "L87"}, {"id": "di_usecasemodule_usecasemodule_provideupdatesociallinksusecase", "label": ".provideUpdateSocialLinksUseCase()", "file_type": "code", "source_file": "C:\\Users\\USERAS\\Desktop\\where\\where-android\\app\\src\\main\\java\\com\\ovi\\where\\di\\UseCaseModule.kt", "source_location": "L89"}, {"id": "di_usecasemodule_usecasemodule_providesendemailverificationusecase", "label": ".provideSendEmailVerificationUseCase()", "file_type": "code", "source_file": "C:\\Users\\USERAS\\Desktop\\where\\where-android\\app\\src\\main\\java\\com\\ovi\\where\\di\\UseCaseModule.kt", "source_location": "L91"}, {"id": "di_usecasemodule_usecasemodule_providereloaduserusecase", "label": ".provideReloadUserUseCase()", "file_type": "code", "source_file": "C:\\Users\\USERAS\\Desktop\\where\\where-android\\app\\src\\main\\java\\com\\ovi\\where\\di\\UseCaseModule.kt", "source_location": "L92"}, {"id": "di_usecasemodule_usecasemodule_providecompleteprofileusecase", "label": ".provideCompleteProfileUseCase()", "file_type": "code", "source_file": "C:\\Users\\USERAS\\Desktop\\where\\where-android\\app\\src\\main\\java\\com\\ovi\\where\\di\\UseCaseModule.kt", "source_location": "L93"}, {"id": "di_usecasemodule_usecasemodule_providecreategroupusecase", "label": ".provideCreateGroupUseCase()", "file_type": "code", "source_file": "C:\\Users\\USERAS\\Desktop\\where\\where-android\\app\\src\\main\\java\\com\\ovi\\where\\di\\UseCaseModule.kt", "source_location": "L96"}, {"id": "di_usecasemodule_usecasemodule_providegetusergroupsusecase", "label": ".provideGetUserGroupsUseCase()", "file_type": "code", "source_file": "C:\\Users\\USERAS\\Desktop\\where\\where-android\\app\\src\\main\\java\\com\\ovi\\where\\di\\UseCaseModule.kt", "source_location": "L97"}, {"id": "di_usecasemodule_usecasemodule_providegetgroupusecase", "label": ".provideGetGroupUseCase()", "file_type": "code", "source_file": "C:\\Users\\USERAS\\Desktop\\where\\where-android\\app\\src\\main\\java\\com\\ovi\\where\\di\\UseCaseModule.kt", "source_location": "L98"}, {"id": "di_usecasemodule_usecasemodule_providejoingroupusecase", "label": ".provideJoinGroupUseCase()", "file_type": "code", "source_file": "C:\\Users\\USERAS\\Desktop\\where\\where-android\\app\\src\\main\\java\\com\\ovi\\where\\di\\UseCaseModule.kt", "source_location": "L99"}, {"id": "di_usecasemodule_usecasemodule_provideleavegroupusecase", "label": ".provideLeaveGroupUseCase()", "file_type": "code", "source_file": "C:\\Users\\USERAS\\Desktop\\where\\where-android\\app\\src\\main\\java\\com\\ovi\\where\\di\\UseCaseModule.kt", "source_location": "L100"}, {"id": "di_usecasemodule_usecasemodule_provideobservegroupmembersusecase", "label": ".provideObserveGroupMembersUseCase()", "file_type": "code", "source_file": "C:\\Users\\USERAS\\Desktop\\where\\where-android\\app\\src\\main\\java\\com\\ovi\\where\\di\\UseCaseModule.kt", "source_location": "L101"}, {"id": "di_usecasemodule_usecasemodule_providekickmemberusecase", "label": ".provideKickMemberUseCase()", "file_type": "code", "source_file": "C:\\Users\\USERAS\\Desktop\\where\\where-android\\app\\src\\main\\java\\com\\ovi\\where\\di\\UseCaseModule.kt", "source_location": "L102"}, {"id": "di_usecasemodule_usecasemodule_providepromotememberusecase", "label": ".providePromoteMemberUseCase()", "file_type": "code", "source_file": "C:\\Users\\USERAS\\Desktop\\where\\where-android\\app\\src\\main\\java\\com\\ovi\\where\\di\\UseCaseModule.kt", "source_location": "L103"}, {"id": "di_usecasemodule_usecasemodule_providedeletegroupusecase", "label": ".provideDeleteGroupUseCase()", "file_type": "code", "source_file": "C:\\Users\\USERAS\\Desktop\\where\\where-android\\app\\src\\main\\java\\com\\ovi\\where\\di\\UseCaseModule.kt", "source_location": "L104"}, {"id": "di_usecasemodule_usecasemodule_provideupdategroupusecase", "label": ".provideUpdateGroupUseCase()", "file_type": "code", "source_file": "C:\\Users\\USERAS\\Desktop\\where\\where-android\\app\\src\\main\\java\\com\\ovi\\where\\di\\UseCaseModule.kt", "source_location": "L105"}, {"id": "di_usecasemodule_usecasemodule_providestartlocationsharingusecase", "label": ".provideStartLocationSharingUseCase()", "file_type": "code", "source_file": "C:\\Users\\USERAS\\Desktop\\where\\where-android\\app\\src\\main\\java\\com\\ovi\\where\\di\\UseCaseModule.kt", "source_location": "L108"}, {"id": "di_usecasemodule_usecasemodule_providestoplocationsharingusecase", "label": ".provideStopLocationSharingUseCase()", "file_type": "code", "source_file": "C:\\Users\\USERAS\\Desktop\\where\\where-android\\app\\src\\main\\java\\com\\ovi\\where\\di\\UseCaseModule.kt", "source_location": "L109"}, {"id": "di_usecasemodule_usecasemodule_provideobservegrouplocationsusecase", "label": ".provideObserveGroupLocationsUseCase()", "file_type": "code", "source_file": "C:\\Users\\USERAS\\Desktop\\where\\where-android\\app\\src\\main\\java\\com\\ovi\\where\\di\\UseCaseModule.kt", "source_location": "L110"}, {"id": "di_usecasemodule_usecasemodule_providesetmeetupdestinationusecase", "label": ".provideSetMeetupDestinationUseCase()", "file_type": "code", "source_file": "C:\\Users\\USERAS\\Desktop\\where\\where-android\\app\\src\\main\\java\\com\\ovi\\where\\di\\UseCaseModule.kt", "source_location": "L111"}, {"id": "di_usecasemodule_usecasemodule_provideclearmeetupdestinationusecase", "label": ".provideClearMeetupDestinationUseCase()", "file_type": "code", "source_file": "C:\\Users\\USERAS\\Desktop\\where\\where-android\\app\\src\\main\\java\\com\\ovi\\where\\di\\UseCaseModule.kt", "source_location": "L112"}, {"id": "di_usecasemodule_usecasemodule_provideobservemeetupdestinationusecase", "label": ".provideObserveMeetupDestinationUseCase()", "file_type": "code", "source_file": "C:\\Users\\USERAS\\Desktop\\where\\where-android\\app\\src\\main\\java\\com\\ovi\\where\\di\\UseCaseModule.kt", "source_location": "L113"}, {"id": "di_usecasemodule_usecasemodule_providedetectarrivalusecase", "label": ".provideDetectArrivalUseCase()", "file_type": "code", "source_file": "C:\\Users\\USERAS\\Desktop\\where\\where-android\\app\\src\\main\\java\\com\\ovi\\where\\di\\UseCaseModule.kt", "source_location": "L114"}, {"id": "di_usecasemodule_usecasemodule_provideupdatemeetupparticipantstatususecase", "label": ".provideUpdateMeetupParticipantStatusUseCase()", "file_type": "code", "source_file": "C:\\Users\\USERAS\\Desktop\\where\\where-android\\app\\src\\main\\java\\com\\ovi\\where\\di\\UseCaseModule.kt", "source_location": "L115"}, {"id": "di_usecasemodule_usecasemodule_provideupdatemeetupparticipantnoteusecase", "label": ".provideUpdateMeetupParticipantNoteUseCase()", "file_type": "code", "source_file": "C:\\Users\\USERAS\\Desktop\\where\\where-android\\app\\src\\main\\java\\com\\ovi\\where\\di\\UseCaseModule.kt", "source_location": "L117"}, {"id": "di_usecasemodule_usecasemodule_providegetmeetuprouteusecase", "label": ".provideGetMeetupRouteUseCase()", "file_type": "code", "source_file": "C:\\Users\\USERAS\\Desktop\\where\\where-android\\app\\src\\main\\java\\com\\ovi\\where\\di\\UseCaseModule.kt", "source_location": "L119"}, {"id": "di_usecasemodule_usecasemodule_providegetusersusecase", "label": ".provideGetUsersUseCase()", "file_type": "code", "source_file": "C:\\Users\\USERAS\\Desktop\\where\\where-android\\app\\src\\main\\java\\com\\ovi\\where\\di\\UseCaseModule.kt", "source_location": "L122"}, {"id": "di_usecasemodule_usecasemodule_providesendfriendrequestusecase", "label": ".provideSendFriendRequestUseCase()", "file_type": "code", "source_file": "C:\\Users\\USERAS\\Desktop\\where\\where-android\\app\\src\\main\\java\\com\\ovi\\where\\di\\UseCaseModule.kt", "source_location": "L125"}, {"id": "di_usecasemodule_usecasemodule_provideacceptfriendrequestusecase", "label": ".provideAcceptFriendRequestUseCase()", "file_type": "code", "source_file": "C:\\Users\\USERAS\\Desktop\\where\\where-android\\app\\src\\main\\java\\com\\ovi\\where\\di\\UseCaseModule.kt", "source_location": "L126"}, {"id": "di_usecasemodule_usecasemodule_providedeclinefriendrequestusecase", "label": ".provideDeclineFriendRequestUseCase()", "file_type": "code", "source_file": "C:\\Users\\USERAS\\Desktop\\where\\where-android\\app\\src\\main\\java\\com\\ovi\\where\\di\\UseCaseModule.kt", "source_location": "L127"}, {"id": "di_usecasemodule_usecasemodule_provideremovefriendusecase", "label": ".provideRemoveFriendUseCase()", "file_type": "code", "source_file": "C:\\Users\\USERAS\\Desktop\\where\\where-android\\app\\src\\main\\java\\com\\ovi\\where\\di\\UseCaseModule.kt", "source_location": "L128"}, {"id": "di_usecasemodule_usecasemodule_provideobservefriendsusecase", "label": ".provideObserveFriendsUseCase()", "file_type": "code", "source_file": "C:\\Users\\USERAS\\Desktop\\where\\where-android\\app\\src\\main\\java\\com\\ovi\\where\\di\\UseCaseModule.kt", "source_location": "L129"}, {"id": "di_usecasemodule_usecasemodule_providegetfriendshipstatususecase", "label": ".provideGetFriendshipStatusUseCase()", "file_type": "code", "source_file": "C:\\Users\\USERAS\\Desktop\\where\\where-android\\app\\src\\main\\java\\com\\ovi\\where\\di\\UseCaseModule.kt", "source_location": "L130"}, {"id": "di_usecasemodule_usecasemodule_provideobserveallfriendlocationsusecase", "label": ".provideObserveAllFriendLocationsUseCase()", "file_type": "code", "source_file": "C:\\Users\\USERAS\\Desktop\\where\\where-android\\app\\src\\main\\java\\com\\ovi\\where\\di\\UseCaseModule.kt", "source_location": "L131"}, {"id": "di_usecasemodule_usecasemodule_providecancelfriendrequestusecase", "label": ".provideCancelFriendRequestUseCase()", "file_type": "code", "source_file": "C:\\Users\\USERAS\\Desktop\\where\\where-android\\app\\src\\main\\java\\com\\ovi\\where\\di\\UseCaseModule.kt", "source_location": "L132"}, {"id": "di_usecasemodule_usecasemodule_provideblockuserusecase", "label": ".provideBlockUserUseCase()", "file_type": "code", "source_file": "C:\\Users\\USERAS\\Desktop\\where\\where-android\\app\\src\\main\\java\\com\\ovi\\where\\di\\UseCaseModule.kt", "source_location": "L133"}, {"id": "di_usecasemodule_usecasemodule_provideunblockuserusecase", "label": ".provideUnblockUserUseCase()", "file_type": "code", "source_file": "C:\\Users\\USERAS\\Desktop\\where\\where-android\\app\\src\\main\\java\\com\\ovi\\where\\di\\UseCaseModule.kt", "source_location": "L134"}, {"id": "di_usecasemodule_usecasemodule_provideobserveincomingrequestsusecase", "label": ".provideObserveIncomingRequestsUseCase()", "file_type": "code", "source_file": "C:\\Users\\USERAS\\Desktop\\where\\where-android\\app\\src\\main\\java\\com\\ovi\\where\\di\\UseCaseModule.kt", "source_location": "L135"}, {"id": "di_usecasemodule_usecasemodule_provideobserveoutgoingrequestsusecase", "label": ".provideObserveOutgoingRequestsUseCase()", "file_type": "code", "source_file": "C:\\Users\\USERAS\\Desktop\\where\\where-android\\app\\src\\main\\java\\com\\ovi\\where\\di\\UseCaseModule.kt", "source_location": "L136"}, {"id": "di_usecasemodule_usecasemodule_provideobservesocialsummaryusecase", "label": ".provideObserveSocialSummaryUseCase()", "file_type": "code", "source_file": "C:\\Users\\USERAS\\Desktop\\where\\where-android\\app\\src\\main\\java\\com\\ovi\\where\\di\\UseCaseModule.kt", "source_location": "L137"}, {"id": "di_usecasemodule_usecasemodule_provideobserveblockedusersusecase", "label": ".provideObserveBlockedUsersUseCase()", "file_type": "code", "source_file": "C:\\Users\\USERAS\\Desktop\\where\\where-android\\app\\src\\main\\java\\com\\ovi\\where\\di\\UseCaseModule.kt", "source_location": "L138"}, {"id": "di_usecasemodule_usecasemodule_provideobserveconversationsusecase", "label": ".provideObserveConversationsUseCase()", "file_type": "code", "source_file": "C:\\Users\\USERAS\\Desktop\\where\\where-android\\app\\src\\main\\java\\com\\ovi\\where\\di\\UseCaseModule.kt", "source_location": "L141"}, {"id": "di_usecasemodule_usecasemodule_provideobservemessagesusecase", "label": ".provideObserveMessagesUseCase()", "file_type": "code", "source_file": "C:\\Users\\USERAS\\Desktop\\where\\where-android\\app\\src\\main\\java\\com\\ovi\\where\\di\\UseCaseModule.kt", "source_location": "L142"}, {"id": "di_usecasemodule_usecasemodule_providegetorcreatedirectconversationusecase", "label": ".provideGetOrCreateDirectConversationUseCase()", "file_type": "code", "source_file": "C:\\Users\\USERAS\\Desktop\\where\\where-android\\app\\src\\main\\java\\com\\ovi\\where\\di\\UseCaseModule.kt", "source_location": "L143"}, {"id": "di_usecasemodule_usecasemodule_providecreategroupconversationusecase", "label": ".provideCreateGroupConversationUseCase()", "file_type": "code", "source_file": "C:\\Users\\USERAS\\Desktop\\where\\where-android\\app\\src\\main\\java\\com\\ovi\\where\\di\\UseCaseModule.kt", "source_location": "L144"}, {"id": "di_usecasemodule_usecasemodule_providesendmessageusecase", "label": ".provideSendMessageUseCase()", "file_type": "code", "source_file": "C:\\Users\\USERAS\\Desktop\\where\\where-android\\app\\src\\main\\java\\com\\ovi\\where\\di\\UseCaseModule.kt", "source_location": "L145"}, {"id": "di_usecasemodule_usecasemodule_providesendlocationmessageusecase", "label": ".provideSendLocationMessageUseCase()", "file_type": "code", "source_file": "C:\\Users\\USERAS\\Desktop\\where\\where-android\\app\\src\\main\\java\\com\\ovi\\where\\di\\UseCaseModule.kt", "source_location": "L146"}, {"id": "di_usecasemodule_usecasemodule_providemarkconversationreadusecase", "label": ".provideMarkConversationReadUseCase()", "file_type": "code", "source_file": "C:\\Users\\USERAS\\Desktop\\where\\where-android\\app\\src\\main\\java\\com\\ovi\\where\\di\\UseCaseModule.kt", "source_location": "L147"}, {"id": "di_usecasemodule_usecasemodule_providefetchlinkpreviewusecase", "label": ".provideFetchLinkPreviewUseCase()", "file_type": "code", "source_file": "C:\\Users\\USERAS\\Desktop\\where\\where-android\\app\\src\\main\\java\\com\\ovi\\where\\di\\UseCaseModule.kt", "source_location": "L148"}, {"id": "di_usecasemodule_usecasemodule_providesendvoicemessageusecase", "label": ".provideSendVoiceMessageUseCase()", "file_type": "code", "source_file": "C:\\Users\\USERAS\\Desktop\\where\\where-android\\app\\src\\main\\java\\com\\ovi\\where\\di\\UseCaseModule.kt", "source_location": "L149"}], "edges": [{"source": "c_users_useras_desktop_where_where_android_app_src_main_java_com_ovi_where_di_usecasemodule_kt", "target": "di_usecasemodule_usecasemodule", "relation": "contains", "confidence": "EXTRACTED", "source_file": "C:\\Users\\USERAS\\Desktop\\where\\where-android\\app\\src\\main\\java\\com\\ovi\\where\\di\\UseCaseModule.kt", "source_location": "L72", "weight": 1.0}, {"source": "di_usecasemodule_usecasemodule", "target": "di_usecasemodule_usecasemodule_providesigninusecase", "relation": "method", "confidence": "EXTRACTED", "source_file": "C:\\Users\\USERAS\\Desktop\\where\\where-android\\app\\src\\main\\java\\com\\ovi\\where\\di\\UseCaseModule.kt", "source_location": "L77", "weight": 1.0}, {"source": "di_usecasemodule_usecasemodule", "target": "di_usecasemodule_usecasemodule_provideregisterusecase", "relation": "method", "confidence": "EXTRACTED", "source_file": "C:\\Users\\USERAS\\Desktop\\where\\where-android\\app\\src\\main\\java\\com\\ovi\\where\\di\\UseCaseModule.kt", "source_location": "L78", "weight": 1.0}, {"source": "di_usecasemodule_usecasemodule", "target": "di_usecasemodule_usecasemodule_provideobservecurrentuserusecase", "relation": "method", "confidence": "EXTRACTED", "source_file": "C:\\Users\\USERAS\\Desktop\\where\\where-android\\app\\src\\main\\java\\com\\ovi\\where\\di\\UseCaseModule.kt", "source_location": "L79", "weight": 1.0}, {"source": "di_usecasemodule_usecasemodule", "target": "di_usecasemodule_usecasemodule_providesignoutusecase", "relation": "method", "confidence": "EXTRACTED", "source_file": "C:\\Users\\USERAS\\Desktop\\where\\where-android\\app\\src\\main\\java\\com\\ovi\\where\\di\\UseCaseModule.kt", "source_location": "L80", "weight": 1.0}, {"source": "di_usecasemodule_usecasemodule", "target": "di_usecasemodule_usecasemodule_providegooglesigninusecase", "relation": "method", "confidence": "EXTRACTED", "source_file": "C:\\Users\\USERAS\\Desktop\\where\\where-android\\app\\src\\main\\java\\com\\ovi\\where\\di\\UseCaseModule.kt", "source_location": "L81", "weight": 1.0}, {"source": "di_usecasemodule_usecasemodule", "target": "di_usecasemodule_usecasemodule_provideresetpasswordusecase", "relation": "method", "confidence": "EXTRACTED", "source_file": "C:\\Users\\USERAS\\Desktop\\where\\where-android\\app\\src\\main\\java\\com\\ovi\\where\\di\\UseCaseModule.kt", "source_location": "L82", "weight": 1.0}, {"source": "di_usecasemodule_usecasemodule", "target": "di_usecasemodule_usecasemodule_provideupdateprofileusecase", "relation": "method", "confidence": "EXTRACTED", "source_file": "C:\\Users\\USERAS\\Desktop\\where\\where-android\\app\\src\\main\\java\\com\\ovi\\where\\di\\UseCaseModule.kt", "source_location": "L83", "weight": 1.0}, {"source": "di_usecasemodule_usecasemodule", "target": "di_usecasemodule_usecasemodule_provideupdatebiousecase", "relation": "method", "confidence": "EXTRACTED", "source_file": "C:\\Users\\USERAS\\Desktop\\where\\where-android\\app\\src\\main\\java\\com\\ovi\\where\\di\\UseCaseModule.kt", "source_location": "L84", "weight": 1.0}, {"source": "di_usecasemodule_usecasemodule", "target": "di_usecasemodule_usecasemodule_provideupdateusernameusecase", "relation": "method", "confidence": "EXTRACTED", "source_file": "C:\\Users\\USERAS\\Desktop\\where\\where-android\\app\\src\\main\\java\\com\\ovi\\where\\di\\UseCaseModule.kt", "source_location": "L85", "weight": 1.0}, {"source": "di_usecasemodule_usecasemodule", "target": "di_usecasemodule_usecasemodule_providecheckusernameavailableusecase", "relation": "method", "confidence": "EXTRACTED", "source_file": "C:\\Users\\USERAS\\Desktop\\where\\where-android\\app\\src\\main\\java\\com\\ovi\\where\\di\\UseCaseModule.kt", "source_location": "L86", "weight": 1.0}, {"source": "di_usecasemodule_usecasemodule", "target": "di_usecasemodule_usecasemodule_provideupdatehomeusecase", "relation": "method", "confidence": "EXTRACTED", "source_file": "C:\\Users\\USERAS\\Desktop\\where\\where-android\\app\\src\\main\\java\\com\\ovi\\where\\di\\UseCaseModule.kt", "source_location": "L87", "weight": 1.0}, {"source": "di_usecasemodule_usecasemodule", "target": "di_usecasemodule_usecasemodule_provideupdatesociallinksusecase", "relation": "method", "confidence": "EXTRACTED", "source_file": "C:\\Users\\USERAS\\Desktop\\where\\where-android\\app\\src\\main\\java\\com\\ovi\\where\\di\\UseCaseModule.kt", "source_location": "L89", "weight": 1.0}, {"source": "di_usecasemodule_usecasemodule", "target": "di_usecasemodule_usecasemodule_providesendemailverificationusecase", "relation": "method", "confidence": "EXTRACTED", "source_file": "C:\\Users\\USERAS\\Desktop\\where\\where-android\\app\\src\\main\\java\\com\\ovi\\where\\di\\UseCaseModule.kt", "source_location": "L91", "weight": 1.0}, {"source": "di_usecasemodule_usecasemodule", "target": "di_usecasemodule_usecasemodule_providereloaduserusecase", "relation": "method", "confidence": "EXTRACTED", "source_file": "C:\\Users\\USERAS\\Desktop\\where\\where-android\\app\\src\\main\\java\\com\\ovi\\where\\di\\UseCaseModule.kt", "source_location": "L92", "weight": 1.0}, {"source": "di_usecasemodule_usecasemodule", "target": "di_usecasemodule_usecasemodule_providecompleteprofileusecase", "relation": "method", "confidence": "EXTRACTED", "source_file": "C:\\Users\\USERAS\\Desktop\\where\\where-android\\app\\src\\main\\java\\com\\ovi\\where\\di\\UseCaseModule.kt", "source_location": "L93", "weight": 1.0}, {"source": "di_usecasemodule_usecasemodule", "target": "di_usecasemodule_usecasemodule_providecreategroupusecase", "relation": "method", "confidence": "EXTRACTED", "source_file": "C:\\Users\\USERAS\\Desktop\\where\\where-android\\app\\src\\main\\java\\com\\ovi\\where\\di\\UseCaseModule.kt", "source_location": "L96", "weight": 1.0}, {"source": "di_usecasemodule_usecasemodule", "target": "di_usecasemodule_usecasemodule_providegetusergroupsusecase", "relation": "method", "confidence": "EXTRACTED", "source_file": "C:\\Users\\USERAS\\Desktop\\where\\where-android\\app\\src\\main\\java\\com\\ovi\\where\\di\\UseCaseModule.kt", "source_location": "L97", "weight": 1.0}, {"source": "di_usecasemodule_usecasemodule", "target": "di_usecasemodule_usecasemodule_providegetgroupusecase", "relation": "method", "confidence": "EXTRACTED", "source_file": "C:\\Users\\USERAS\\Desktop\\where\\where-android\\app\\src\\main\\java\\com\\ovi\\where\\di\\UseCaseModule.kt", "source_location": "L98", "weight": 1.0}, {"source": "di_usecasemodule_usecasemodule", "target": "di_usecasemodule_usecasemodule_providejoingroupusecase", "relation": "method", "confidence": "EXTRACTED", "source_file": "C:\\Users\\USERAS\\Desktop\\where\\where-android\\app\\src\\main\\java\\com\\ovi\\where\\di\\UseCaseModule.kt", "source_location": "L99", "weight": 1.0}, {"source": "di_usecasemodule_usecasemodule", "target": "di_usecasemodule_usecasemodule_provideleavegroupusecase", "relation": "method", "confidence": "EXTRACTED", "source_file": "C:\\Users\\USERAS\\Desktop\\where\\where-android\\app\\src\\main\\java\\com\\ovi\\where\\di\\UseCaseModule.kt", "source_location": "L100", "weight": 1.0}, {"source": "di_usecasemodule_usecasemodule", "target": "di_usecasemodule_usecasemodule_provideobservegroupmembersusecase", "relation": "method", "confidence": "EXTRACTED", "source_file": "C:\\Users\\USERAS\\Desktop\\where\\where-android\\app\\src\\main\\java\\com\\ovi\\where\\di\\UseCaseModule.kt", "source_location": "L101", "weight": 1.0}, {"source": "di_usecasemodule_usecasemodule", "target": "di_usecasemodule_usecasemodule_providekickmemberusecase", "relation": "method", "confidence": "EXTRACTED", "source_file": "C:\\Users\\USERAS\\Desktop\\where\\where-android\\app\\src\\main\\java\\com\\ovi\\where\\di\\UseCaseModule.kt", "source_location": "L102", "weight": 1.0}, {"source": "di_usecasemodule_usecasemodule", "target": "di_usecasemodule_usecasemodule_providepromotememberusecase", "relation": "method", "confidence": "EXTRACTED", "source_file": "C:\\Users\\USERAS\\Desktop\\where\\where-android\\app\\src\\main\\java\\com\\ovi\\where\\di\\UseCaseModule.kt", "source_location": "L103", "weight": 1.0}, {"source": "di_usecasemodule_usecasemodule", "target": "di_usecasemodule_usecasemodule_providedeletegroupusecase", "relation": "method", "confidence": "EXTRACTED", "source_file": "C:\\Users\\USERAS\\Desktop\\where\\where-android\\app\\src\\main\\java\\com\\ovi\\where\\di\\UseCaseModule.kt", "source_location": "L104", "weight": 1.0}, {"source": "di_usecasemodule_usecasemodule", "target": "di_usecasemodule_usecasemodule_provideupdategroupusecase", "relation": "method", "confidence": "EXTRACTED", "source_file": "C:\\Users\\USERAS\\Desktop\\where\\where-android\\app\\src\\main\\java\\com\\ovi\\where\\di\\UseCaseModule.kt", "source_location": "L105", "weight": 1.0}, {"source": "di_usecasemodule_usecasemodule", "target": "di_usecasemodule_usecasemodule_providestartlocationsharingusecase", "relation": "method", "confidence": "EXTRACTED", "source_file": "C:\\Users\\USERAS\\Desktop\\where\\where-android\\app\\src\\main\\java\\com\\ovi\\where\\di\\UseCaseModule.kt", "source_location": "L108", "weight": 1.0}, {"source": "di_usecasemodule_usecasemodule", "target": "di_usecasemodule_usecasemodule_providestoplocationsharingusecase", "relation": "method", "confidence": "EXTRACTED", "source_file": "C:\\Users\\USERAS\\Desktop\\where\\where-android\\app\\src\\main\\java\\com\\ovi\\where\\di\\UseCaseModule.kt", "source_location": "L109", "weight": 1.0}, {"source": "di_usecasemodule_usecasemodule", "target": "di_usecasemodule_usecasemodule_provideobservegrouplocationsusecase", "relation": "method", "confidence": "EXTRACTED", "source_file": "C:\\Users\\USERAS\\Desktop\\where\\where-android\\app\\src\\main\\java\\com\\ovi\\where\\di\\UseCaseModule.kt", "source_location": "L110", "weight": 1.0}, {"source": "di_usecasemodule_usecasemodule", "target": "di_usecasemodule_usecasemodule_providesetmeetupdestinationusecase", "relation": "method", "confidence": "EXTRACTED", "source_file": "C:\\Users\\USERAS\\Desktop\\where\\where-android\\app\\src\\main\\java\\com\\ovi\\where\\di\\UseCaseModule.kt", "source_location": "L111", "weight": 1.0}, {"source": "di_usecasemodule_usecasemodule", "target": "di_usecasemodule_usecasemodule_provideclearmeetupdestinationusecase", "relation": "method", "confidence": "EXTRACTED", "source_file": "C:\\Users\\USERAS\\Desktop\\where\\where-android\\app\\src\\main\\java\\com\\ovi\\where\\di\\UseCaseModule.kt", "source_location": "L112", "weight": 1.0}, {"source": "di_usecasemodule_usecasemodule", "target": "di_usecasemodule_usecasemodule_provideobservemeetupdestinationusecase", "relation": "method", "confidence": "EXTRACTED", "source_file": "C:\\Users\\USERAS\\Desktop\\where\\where-android\\app\\src\\main\\java\\com\\ovi\\where\\di\\UseCaseModule.kt", "source_location": "L113", "weight": 1.0}, {"source": "di_usecasemodule_usecasemodule", "target": "di_usecasemodule_usecasemodule_providedetectarrivalusecase", "relation": "method", "confidence": "EXTRACTED", "source_file": "C:\\Users\\USERAS\\Desktop\\where\\where-android\\app\\src\\main\\java\\com\\ovi\\where\\di\\UseCaseModule.kt", "source_location": "L114", "weight": 1.0}, {"source": "di_usecasemodule_usecasemodule", "target": "di_usecasemodule_usecasemodule_provideupdatemeetupparticipantstatususecase", "relation": "method", "confidence": "EXTRACTED", "source_file": "C:\\Users\\USERAS\\Desktop\\where\\where-android\\app\\src\\main\\java\\com\\ovi\\where\\di\\UseCaseModule.kt", "source_location": "L115", "weight": 1.0}, {"source": "di_usecasemodule_usecasemodule", "target": "di_usecasemodule_usecasemodule_provideupdatemeetupparticipantnoteusecase", "relation": "method", "confidence": "EXTRACTED", "source_file": "C:\\Users\\USERAS\\Desktop\\where\\where-android\\app\\src\\main\\java\\com\\ovi\\where\\di\\UseCaseModule.kt", "source_location": "L117", "weight": 1.0}, {"source": "di_usecasemodule_usecasemodule", "target": "di_usecasemodule_usecasemodule_providegetmeetuprouteusecase", "relation": "method", "confidence": "EXTRACTED", "source_file": "C:\\Users\\USERAS\\Desktop\\where\\where-android\\app\\src\\main\\java\\com\\ovi\\where\\di\\UseCaseModule.kt", "source_location": "L119", "weight": 1.0}, {"source": "di_usecasemodule_usecasemodule", "target": "di_usecasemodule_usecasemodule_providegetusersusecase", "relation": "method", "confidence": "EXTRACTED", "source_file": "C:\\Users\\USERAS\\Desktop\\where\\where-android\\app\\src\\main\\java\\com\\ovi\\where\\di\\UseCaseModule.kt", "source_location": "L122", "weight": 1.0}, {"source": "di_usecasemodule_usecasemodule", "target": "di_usecasemodule_usecasemodule_providesendfriendrequestusecase", "relation": "method", "confidence": "EXTRACTED", "source_file": "C:\\Users\\USERAS\\Desktop\\where\\where-android\\app\\src\\main\\java\\com\\ovi\\where\\di\\UseCaseModule.kt", "source_location": "L125", "weight": 1.0}, {"source": "di_usecasemodule_usecasemodule", "target": "di_usecasemodule_usecasemodule_provideacceptfriendrequestusecase", "relation": "method", "confidence": "EXTRACTED", "source_file": "C:\\Users\\USERAS\\Desktop\\where\\where-android\\app\\src\\main\\java\\com\\ovi\\where\\di\\UseCaseModule.kt", "source_location": "L126", "weight": 1.0}, {"source": "di_usecasemodule_usecasemodule", "target": "di_usecasemodule_usecasemodule_providedeclinefriendrequestusecase", "relation": "method", "confidence": "EXTRACTED", "source_file": "C:\\Users\\USERAS\\Desktop\\where\\where-android\\app\\src\\main\\java\\com\\ovi\\where\\di\\UseCaseModule.kt", "source_location": "L127", "weight": 1.0}, {"source": "di_usecasemodule_usecasemodule", "target": "di_usecasemodule_usecasemodule_provideremovefriendusecase", "relation": "method", "confidence": "EXTRACTED", "source_file": "C:\\Users\\USERAS\\Desktop\\where\\where-android\\app\\src\\main\\java\\com\\ovi\\where\\di\\UseCaseModule.kt", "source_location": "L128", "weight": 1.0}, {"source": "di_usecasemodule_usecasemodule", "target": "di_usecasemodule_usecasemodule_provideobservefriendsusecase", "relation": "method", "confidence": "EXTRACTED", "source_file": "C:\\Users\\USERAS\\Desktop\\where\\where-android\\app\\src\\main\\java\\com\\ovi\\where\\di\\UseCaseModule.kt", "source_location": "L129", "weight": 1.0}, {"source": "di_usecasemodule_usecasemodule", "target": "di_usecasemodule_usecasemodule_providegetfriendshipstatususecase", "relation": "method", "confidence": "EXTRACTED", "source_file": "C:\\Users\\USERAS\\Desktop\\where\\where-android\\app\\src\\main\\java\\com\\ovi\\where\\di\\UseCaseModule.kt", "source_location": "L130", "weight": 1.0}, {"source": "di_usecasemodule_usecasemodule", "target": "di_usecasemodule_usecasemodule_provideobserveallfriendlocationsusecase", "relation": "method", "confidence": "EXTRACTED", "source_file": "C:\\Users\\USERAS\\Desktop\\where\\where-android\\app\\src\\main\\java\\com\\ovi\\where\\di\\UseCaseModule.kt", "source_location": "L131", "weight": 1.0}, {"source": "di_usecasemodule_usecasemodule", "target": "di_usecasemodule_usecasemodule_providecancelfriendrequestusecase", "relation": "method", "confidence": "EXTRACTED", "source_file": "C:\\Users\\USERAS\\Desktop\\where\\where-android\\app\\src\\main\\java\\com\\ovi\\where\\di\\UseCaseModule.kt", "source_location": "L132", "weight": 1.0}, {"source": "di_usecasemodule_usecasemodule", "target": "di_usecasemodule_usecasemodule_provideblockuserusecase", "relation": "method", "confidence": "EXTRACTED", "source_file": "C:\\Users\\USERAS\\Desktop\\where\\where-android\\app\\src\\main\\java\\com\\ovi\\where\\di\\UseCaseModule.kt", "source_location": "L133", "weight": 1.0}, {"source": "di_usecasemodule_usecasemodule", "target": "di_usecasemodule_usecasemodule_provideunblockuserusecase", "relation": "method", "confidence": "EXTRACTED", "source_file": "C:\\Users\\USERAS\\Desktop\\where\\where-android\\app\\src\\main\\java\\com\\ovi\\where\\di\\UseCaseModule.kt", "source_location": "L134", "weight": 1.0}, {"source": "di_usecasemodule_usecasemodule", "target": "di_usecasemodule_usecasemodule_provideobserveincomingrequestsusecase", "relation": "method", "confidence": "EXTRACTED", "source_file": "C:\\Users\\USERAS\\Desktop\\where\\where-android\\app\\src\\main\\java\\com\\ovi\\where\\di\\UseCaseModule.kt", "source_location": "L135", "weight": 1.0}, {"source": "di_usecasemodule_usecasemodule", "target": "di_usecasemodule_usecasemodule_provideobserveoutgoingrequestsusecase", "relation": "method", "confidence": "EXTRACTED", "source_file": "C:\\Users\\USERAS\\Desktop\\where\\where-android\\app\\src\\main\\java\\com\\ovi\\where\\di\\UseCaseModule.kt", "source_location": "L136", "weight": 1.0}, {"source": "di_usecasemodule_usecasemodule", "target": "di_usecasemodule_usecasemodule_provideobservesocialsummaryusecase", "relation": "method", "confidence": "EXTRACTED", "source_file": "C:\\Users\\USERAS\\Desktop\\where\\where-android\\app\\src\\main\\java\\com\\ovi\\where\\di\\UseCaseModule.kt", "source_location": "L137", "weight": 1.0}, {"source": "di_usecasemodule_usecasemodule", "target": "di_usecasemodule_usecasemodule_provideobserveblockedusersusecase", "relation": "method", "confidence": "EXTRACTED", "source_file": "C:\\Users\\USERAS\\Desktop\\where\\where-android\\app\\src\\main\\java\\com\\ovi\\where\\di\\UseCaseModule.kt", "source_location": "L138", "weight": 1.0}, {"source": "di_usecasemodule_usecasemodule", "target": "di_usecasemodule_usecasemodule_provideobserveconversationsusecase", "relation": "method", "confidence": "EXTRACTED", "source_file": "C:\\Users\\USERAS\\Desktop\\where\\where-android\\app\\src\\main\\java\\com\\ovi\\where\\di\\UseCaseModule.kt", "source_location": "L141", "weight": 1.0}, {"source": "di_usecasemodule_usecasemodule", "target": "di_usecasemodule_usecasemodule_provideobservemessagesusecase", "relation": "method", "confidence": "EXTRACTED", "source_file": "C:\\Users\\USERAS\\Desktop\\where\\where-android\\app\\src\\main\\java\\com\\ovi\\where\\di\\UseCaseModule.kt", "source_location": "L142", "weight": 1.0}, {"source": "di_usecasemodule_usecasemodule", "target": "di_usecasemodule_usecasemodule_providegetorcreatedirectconversationusecase", "relation": "method", "confidence": "EXTRACTED", "source_file": "C:\\Users\\USERAS\\Desktop\\where\\where-android\\app\\src\\main\\java\\com\\ovi\\where\\di\\UseCaseModule.kt", "source_location": "L143", "weight": 1.0}, {"source": "di_usecasemodule_usecasemodule", "target": "di_usecasemodule_usecasemodule_providecreategroupconversationusecase", "relation": "method", "confidence": "EXTRACTED", "source_file": "C:\\Users\\USERAS\\Desktop\\where\\where-android\\app\\src\\main\\java\\com\\ovi\\where\\di\\UseCaseModule.kt", "source_location": "L144", "weight": 1.0}, {"source": "di_usecasemodule_usecasemodule", "target": "di_usecasemodule_usecasemodule_providesendmessageusecase", "relation": "method", "confidence": "EXTRACTED", "source_file": "C:\\Users\\USERAS\\Desktop\\where\\where-android\\app\\src\\main\\java\\com\\ovi\\where\\di\\UseCaseModule.kt", "source_location": "L145", "weight": 1.0}, {"source": "di_usecasemodule_usecasemodule", "target": "di_usecasemodule_usecasemodule_providesendlocationmessageusecase", "relation": "method", "confidence": "EXTRACTED", "source_file": "C:\\Users\\USERAS\\Desktop\\where\\where-android\\app\\src\\main\\java\\com\\ovi\\where\\di\\UseCaseModule.kt", "source_location": "L146", "weight": 1.0}, {"source": "di_usecasemodule_usecasemodule", "target": "di_usecasemodule_usecasemodule_providemarkconversationreadusecase", "relation": "method", "confidence": "EXTRACTED", "source_file": "C:\\Users\\USERAS\\Desktop\\where\\where-android\\app\\src\\main\\java\\com\\ovi\\where\\di\\UseCaseModule.kt", "source_location": "L147", "weight": 1.0}, {"source": "di_usecasemodule_usecasemodule", "target": "di_usecasemodule_usecasemodule_providefetchlinkpreviewusecase", "relation": "method", "confidence": "EXTRACTED", "source_file": "C:\\Users\\USERAS\\Desktop\\where\\where-android\\app\\src\\main\\java\\com\\ovi\\where\\di\\UseCaseModule.kt", "source_location": "L148", "weight": 1.0}, {"source": "di_usecasemodule_usecasemodule", "target": "di_usecasemodule_usecasemodule_providesendvoicemessageusecase", "relation": "method", "confidence": "EXTRACTED", "source_file": "C:\\Users\\USERAS\\Desktop\\where\\where-android\\app\\src\\main\\java\\com\\ovi\\where\\di\\UseCaseModule.kt", "source_location": "L149", "weight": 1.0}], "raw_calls": [{"caller_nid": "di_usecasemodule_usecasemodule_providesigninusecase", "callee": "SignInUseCase", "is_member_call": false, "source_file": "C:\\Users\\USERAS\\Desktop\\where\\where-android\\app\\src\\main\\java\\com\\ovi\\where\\di\\UseCaseModule.kt", "source_location": "L77"}, {"caller_nid": "di_usecasemodule_usecasemodule_provideregisterusecase", "callee": "RegisterUseCase", "is_member_call": false, "source_file": "C:\\Users\\USERAS\\Desktop\\where\\where-android\\app\\src\\main\\java\\com\\ovi\\where\\di\\UseCaseModule.kt", "source_location": "L78"}, {"caller_nid": "di_usecasemodule_usecasemodule_provideobservecurrentuserusecase", "callee": "ObserveCurrentUserUseCase", "is_member_call": false, "source_file": "C:\\Users\\USERAS\\Desktop\\where\\where-android\\app\\src\\main\\java\\com\\ovi\\where\\di\\UseCaseModule.kt", "source_location": "L79"}, {"caller_nid": "di_usecasemodule_usecasemodule_providesignoutusecase", "callee": "SignOutUseCase", "is_member_call": false, "source_file": "C:\\Users\\USERAS\\Desktop\\where\\where-android\\app\\src\\main\\java\\com\\ovi\\where\\di\\UseCaseModule.kt", "source_location": "L80"}, {"caller_nid": "di_usecasemodule_usecasemodule_providegooglesigninusecase", "callee": "GoogleSignInUseCase", "is_member_call": false, "source_file": "C:\\Users\\USERAS\\Desktop\\where\\where-android\\app\\src\\main\\java\\com\\ovi\\where\\di\\UseCaseModule.kt", "source_location": "L81"}, {"caller_nid": "di_usecasemodule_usecasemodule_provideresetpasswordusecase", "callee": "ResetPasswordUseCase", "is_member_call": false, "source_file": "C:\\Users\\USERAS\\Desktop\\where\\where-android\\app\\src\\main\\java\\com\\ovi\\where\\di\\UseCaseModule.kt", "source_location": "L82"}, {"caller_nid": "di_usecasemodule_usecasemodule_provideupdateprofileusecase", "callee": "UpdateProfileUseCase", "is_member_call": false, "source_file": "C:\\Users\\USERAS\\Desktop\\where\\where-android\\app\\src\\main\\java\\com\\ovi\\where\\di\\UseCaseModule.kt", "source_location": "L83"}, {"caller_nid": "di_usecasemodule_usecasemodule_provideupdatebiousecase", "callee": "UpdateBioUseCase", "is_member_call": false, "source_file": "C:\\Users\\USERAS\\Desktop\\where\\where-android\\app\\src\\main\\java\\com\\ovi\\where\\di\\UseCaseModule.kt", "source_location": "L84"}, {"caller_nid": "di_usecasemodule_usecasemodule_provideupdateusernameusecase", "callee": "UpdateUsernameUseCase", "is_member_call": false, "source_file": "C:\\Users\\USERAS\\Desktop\\where\\where-android\\app\\src\\main\\java\\com\\ovi\\where\\di\\UseCaseModule.kt", "source_location": "L85"}, {"caller_nid": "di_usecasemodule_usecasemodule_providecheckusernameavailableusecase", "callee": "CheckUsernameAvailableUseCase", "is_member_call": false, "source_file": "C:\\Users\\USERAS\\Desktop\\where\\where-android\\app\\src\\main\\java\\com\\ovi\\where\\di\\UseCaseModule.kt", "source_location": "L86"}, {"caller_nid": "di_usecasemodule_usecasemodule_provideupdatehomeusecase", "callee": "UpdateHomeUseCase", "is_member_call": true, "source_file": "C:\\Users\\USERAS\\Desktop\\where\\where-android\\app\\src\\main\\java\\com\\ovi\\where\\di\\UseCaseModule.kt", "source_location": "L88"}, {"caller_nid": "di_usecasemodule_usecasemodule_provideupdatesociallinksusecase", "callee": "UpdateSocialLinksUseCase", "is_member_call": true, "source_file": "C:\\Users\\USERAS\\Desktop\\where\\where-android\\app\\src\\main\\java\\com\\ovi\\where\\di\\UseCaseModule.kt", "source_location": "L90"}, {"caller_nid": "di_usecasemodule_usecasemodule_providesendemailverificationusecase", "callee": "SendEmailVerificationUseCase", "is_member_call": false, "source_file": "C:\\Users\\USERAS\\Desktop\\where\\where-android\\app\\src\\main\\java\\com\\ovi\\where\\di\\UseCaseModule.kt", "source_location": "L91"}, {"caller_nid": "di_usecasemodule_usecasemodule_providereloaduserusecase", "callee": "ReloadUserUseCase", "is_member_call": false, "source_file": "C:\\Users\\USERAS\\Desktop\\where\\where-android\\app\\src\\main\\java\\com\\ovi\\where\\di\\UseCaseModule.kt", "source_location": "L92"}, {"caller_nid": "di_usecasemodule_usecasemodule_providecompleteprofileusecase", "callee": "CompleteProfileUseCase", "is_member_call": false, "source_file": "C:\\Users\\USERAS\\Desktop\\where\\where-android\\app\\src\\main\\java\\com\\ovi\\where\\di\\UseCaseModule.kt", "source_location": "L93"}, {"caller_nid": "di_usecasemodule_usecasemodule_providecreategroupusecase", "callee": "CreateGroupUseCase", "is_member_call": false, "source_file": "C:\\Users\\USERAS\\Desktop\\where\\where-android\\app\\src\\main\\java\\com\\ovi\\where\\di\\UseCaseModule.kt", "source_location": "L96"}, {"caller_nid": "di_usecasemodule_usecasemodule_providegetusergroupsusecase", "callee": "GetUserGroupsUseCase", "is_member_call": false, "source_file": "C:\\Users\\USERAS\\Desktop\\where\\where-android\\app\\src\\main\\java\\com\\ovi\\where\\di\\UseCaseModule.kt", "source_location": "L97"}, {"caller_nid": "di_usecasemodule_usecasemodule_providegetgroupusecase", "callee": "GetGroupUseCase", "is_member_call": false, "source_file": "C:\\Users\\USERAS\\Desktop\\where\\where-android\\app\\src\\main\\java\\com\\ovi\\where\\di\\UseCaseModule.kt", "source_location": "L98"}, {"caller_nid": "di_usecasemodule_usecasemodule_providejoingroupusecase", "callee": "JoinGroupUseCase", "is_member_call": false, "source_file": "C:\\Users\\USERAS\\Desktop\\where\\where-android\\app\\src\\main\\java\\com\\ovi\\where\\di\\UseCaseModule.kt", "source_location": "L99"}, {"caller_nid": "di_usecasemodule_usecasemodule_provideleavegroupusecase", "callee": "LeaveGroupUseCase", "is_member_call": false, "source_file": "C:\\Users\\USERAS\\Desktop\\where\\where-android\\app\\src\\main\\java\\com\\ovi\\where\\di\\UseCaseModule.kt", "source_location": "L100"}, {"caller_nid": "di_usecasemodule_usecasemodule_provideobservegroupmembersusecase", "callee": "ObserveGroupMembersUseCase", "is_member_call": false, "source_file": "C:\\Users\\USERAS\\Desktop\\where\\where-android\\app\\src\\main\\java\\com\\ovi\\where\\di\\UseCaseModule.kt", "source_location": "L101"}, {"caller_nid": "di_usecasemodule_usecasemodule_providekickmemberusecase", "callee": "KickMemberUseCase", "is_member_call": false, "source_file": "C:\\Users\\USERAS\\Desktop\\where\\where-android\\app\\src\\main\\java\\com\\ovi\\where\\di\\UseCaseModule.kt", "source_location": "L102"}, {"caller_nid": "di_usecasemodule_usecasemodule_providepromotememberusecase", "callee": "PromoteMemberUseCase", "is_member_call": false, "source_file": "C:\\Users\\USERAS\\Desktop\\where\\where-android\\app\\src\\main\\java\\com\\ovi\\where\\di\\UseCaseModule.kt", "source_location": "L103"}, {"caller_nid": "di_usecasemodule_usecasemodule_providedeletegroupusecase", "callee": "DeleteGroupUseCase", "is_member_call": false, "source_file": "C:\\Users\\USERAS\\Desktop\\where\\where-android\\app\\src\\main\\java\\com\\ovi\\where\\di\\UseCaseModule.kt", "source_location": "L104"}, {"caller_nid": "di_usecasemodule_usecasemodule_provideupdategroupusecase", "callee": "UpdateGroupUseCase", "is_member_call": false, "source_file": "C:\\Users\\USERAS\\Desktop\\where\\where-android\\app\\src\\main\\java\\com\\ovi\\where\\di\\UseCaseModule.kt", "source_location": "L105"}, {"caller_nid": "di_usecasemodule_usecasemodule_providestartlocationsharingusecase", "callee": "StartLocationSharingUseCase", "is_member_call": false, "source_file": "C:\\Users\\USERAS\\Desktop\\where\\where-android\\app\\src\\main\\java\\com\\ovi\\where\\di\\UseCaseModule.kt", "source_location": "L108"}, {"caller_nid": "di_usecasemodule_usecasemodule_providestoplocationsharingusecase", "callee": "StopLocationSharingUseCase", "is_member_call": false, "source_file": "C:\\Users\\USERAS\\Desktop\\where\\where-android\\app\\src\\main\\java\\com\\ovi\\where\\di\\UseCaseModule.kt", "source_location": "L109"}, {"caller_nid": "di_usecasemodule_usecasemodule_provideobservegrouplocationsusecase", "callee": "ObserveGroupLocationsUseCase", "is_member_call": false, "source_file": "C:\\Users\\USERAS\\Desktop\\where\\where-android\\app\\src\\main\\java\\com\\ovi\\where\\di\\UseCaseModule.kt", "source_location": "L110"}, {"caller_nid": "di_usecasemodule_usecasemodule_providesetmeetupdestinationusecase", "callee": "SetMeetupDestinationUseCase", "is_member_call": false, "source_file": "C:\\Users\\USERAS\\Desktop\\where\\where-android\\app\\src\\main\\java\\com\\ovi\\where\\di\\UseCaseModule.kt", "source_location": "L111"}, {"caller_nid": "di_usecasemodule_usecasemodule_provideclearmeetupdestinationusecase", "callee": "ClearMeetupDestinationUseCase", "is_member_call": false, "source_file": "C:\\Users\\USERAS\\Desktop\\where\\where-android\\app\\src\\main\\java\\com\\ovi\\where\\di\\UseCaseModule.kt", "source_location": "L112"}, {"caller_nid": "di_usecasemodule_usecasemodule_provideobservemeetupdestinationusecase", "callee": "ObserveMeetupDestinationUseCase", "is_member_call": false, "source_file": "C:\\Users\\USERAS\\Desktop\\where\\where-android\\app\\src\\main\\java\\com\\ovi\\where\\di\\UseCaseModule.kt", "source_location": "L113"}, {"caller_nid": "di_usecasemodule_usecasemodule_providedetectarrivalusecase", "callee": "DetectArrivalUseCase", "is_member_call": false, "source_file": "C:\\Users\\USERAS\\Desktop\\where\\where-android\\app\\src\\main\\java\\com\\ovi\\where\\di\\UseCaseModule.kt", "source_location": "L114"}, {"caller_nid": "di_usecasemodule_usecasemodule_provideupdatemeetupparticipantstatususecase", "callee": "UpdateMeetupParticipantStatusUseCase", "is_member_call": true, "source_file": "C:\\Users\\USERAS\\Desktop\\where\\where-android\\app\\src\\main\\java\\com\\ovi\\where\\di\\UseCaseModule.kt", "source_location": "L116"}, {"caller_nid": "di_usecasemodule_usecasemodule_provideupdatemeetupparticipantnoteusecase", "callee": "UpdateMeetupParticipantNoteUseCase", "is_member_call": true, "source_file": "C:\\Users\\USERAS\\Desktop\\where\\where-android\\app\\src\\main\\java\\com\\ovi\\where\\di\\UseCaseModule.kt", "source_location": "L118"}, {"caller_nid": "di_usecasemodule_usecasemodule_providegetmeetuprouteusecase", "callee": "GetMeetupRouteUseCase", "is_member_call": false, "source_file": "C:\\Users\\USERAS\\Desktop\\where\\where-android\\app\\src\\main\\java\\com\\ovi\\where\\di\\UseCaseModule.kt", "source_location": "L119"}, {"caller_nid": "di_usecasemodule_usecasemodule_providegetusersusecase", "callee": "GetUsersUseCase", "is_member_call": false, "source_file": "C:\\Users\\USERAS\\Desktop\\where\\where-android\\app\\src\\main\\java\\com\\ovi\\where\\di\\UseCaseModule.kt", "source_location": "L122"}, {"caller_nid": "di_usecasemodule_usecasemodule_providesendfriendrequestusecase", "callee": "SendFriendRequestUseCase", "is_member_call": false, "source_file": "C:\\Users\\USERAS\\Desktop\\where\\where-android\\app\\src\\main\\java\\com\\ovi\\where\\di\\UseCaseModule.kt", "source_location": "L125"}, {"caller_nid": "di_usecasemodule_usecasemodule_provideacceptfriendrequestusecase", "callee": "AcceptFriendRequestUseCase", "is_member_call": false, "source_file": "C:\\Users\\USERAS\\Desktop\\where\\where-android\\app\\src\\main\\java\\com\\ovi\\where\\di\\UseCaseModule.kt", "source_location": "L126"}, {"caller_nid": "di_usecasemodule_usecasemodule_providedeclinefriendrequestusecase", "callee": "DeclineFriendRequestUseCase", "is_member_call": false, "source_file": "C:\\Users\\USERAS\\Desktop\\where\\where-android\\app\\src\\main\\java\\com\\ovi\\where\\di\\UseCaseModule.kt", "source_location": "L127"}, {"caller_nid": "di_usecasemodule_usecasemodule_provideremovefriendusecase", "callee": "RemoveFriendUseCase", "is_member_call": false, "source_file": "C:\\Users\\USERAS\\Desktop\\where\\where-android\\app\\src\\main\\java\\com\\ovi\\where\\di\\UseCaseModule.kt", "source_location": "L128"}, {"caller_nid": "di_usecasemodule_usecasemodule_provideobservefriendsusecase", "callee": "ObserveFriendsUseCase", "is_member_call": false, "source_file": "C:\\Users\\USERAS\\Desktop\\where\\where-android\\app\\src\\main\\java\\com\\ovi\\where\\di\\UseCaseModule.kt", "source_location": "L129"}, {"caller_nid": "di_usecasemodule_usecasemodule_providegetfriendshipstatususecase", "callee": "GetFriendshipStatusUseCase", "is_member_call": false, "source_file": "C:\\Users\\USERAS\\Desktop\\where\\where-android\\app\\src\\main\\java\\com\\ovi\\where\\di\\UseCaseModule.kt", "source_location": "L130"}, {"caller_nid": "di_usecasemodule_usecasemodule_provideobserveallfriendlocationsusecase", "callee": "ObserveAllFriendLocationsUseCase", "is_member_call": false, "source_file": "C:\\Users\\USERAS\\Desktop\\where\\where-android\\app\\src\\main\\java\\com\\ovi\\where\\di\\UseCaseModule.kt", "source_location": "L131"}, {"caller_nid": "di_usecasemodule_usecasemodule_providecancelfriendrequestusecase", "callee": "CancelFriendRequestUseCase", "is_member_call": false, "source_file": "C:\\Users\\USERAS\\Desktop\\where\\where-android\\app\\src\\main\\java\\com\\ovi\\where\\di\\UseCaseModule.kt", "source_location": "L132"}, {"caller_nid": "di_usecasemodule_usecasemodule_provideblockuserusecase", "callee": "BlockUserUseCase", "is_member_call": false, "source_file": "C:\\Users\\USERAS\\Desktop\\where\\where-android\\app\\src\\main\\java\\com\\ovi\\where\\di\\UseCaseModule.kt", "source_location": "L133"}, {"caller_nid": "di_usecasemodule_usecasemodule_provideunblockuserusecase", "callee": "UnblockUserUseCase", "is_member_call": false, "source_file": "C:\\Users\\USERAS\\Desktop\\where\\where-android\\app\\src\\main\\java\\com\\ovi\\where\\di\\UseCaseModule.kt", "source_location": "L134"}, {"caller_nid": "di_usecasemodule_usecasemodule_provideobserveincomingrequestsusecase", "callee": "ObserveIncomingRequestsUseCase", "is_member_call": false, "source_file": "C:\\Users\\USERAS\\Desktop\\where\\where-android\\app\\src\\main\\java\\com\\ovi\\where\\di\\UseCaseModule.kt", "source_location": "L135"}, {"caller_nid": "di_usecasemodule_usecasemodule_provideobserveoutgoingrequestsusecase", "callee": "ObserveOutgoingRequestsUseCase", "is_member_call": false, "source_file": "C:\\Users\\USERAS\\Desktop\\where\\where-android\\app\\src\\main\\java\\com\\ovi\\where\\di\\UseCaseModule.kt", "source_location": "L136"}, {"caller_nid": "di_usecasemodule_usecasemodule_provideobservesocialsummaryusecase", "callee": "ObserveSocialSummaryUseCase", "is_member_call": false, "source_file": "C:\\Users\\USERAS\\Desktop\\where\\where-android\\app\\src\\main\\java\\com\\ovi\\where\\di\\UseCaseModule.kt", "source_location": "L137"}, {"caller_nid": "di_usecasemodule_usecasemodule_provideobserveblockedusersusecase", "callee": "ObserveBlockedUsersUseCase", "is_member_call": false, "source_file": "C:\\Users\\USERAS\\Desktop\\where\\where-android\\app\\src\\main\\java\\com\\ovi\\where\\di\\UseCaseModule.kt", "source_location": "L138"}, {"caller_nid": "di_usecasemodule_usecasemodule_provideobserveconversationsusecase", "callee": "ObserveConversationsUseCase", "is_member_call": false, "source_file": "C:\\Users\\USERAS\\Desktop\\where\\where-android\\app\\src\\main\\java\\com\\ovi\\where\\di\\UseCaseModule.kt", "source_location": "L141"}, {"caller_nid": "di_usecasemodule_usecasemodule_provideobservemessagesusecase", "callee": "ObserveMessagesUseCase", "is_member_call": false, "source_file": "C:\\Users\\USERAS\\Desktop\\where\\where-android\\app\\src\\main\\java\\com\\ovi\\where\\di\\UseCaseModule.kt", "source_location": "L142"}, {"caller_nid": "di_usecasemodule_usecasemodule_providegetorcreatedirectconversationusecase", "callee": "GetOrCreateDirectConversationUseCase", "is_member_call": false, "source_file": "C:\\Users\\USERAS\\Desktop\\where\\where-android\\app\\src\\main\\java\\com\\ovi\\where\\di\\UseCaseModule.kt", "source_location": "L143"}, {"caller_nid": "di_usecasemodule_usecasemodule_providecreategroupconversationusecase", "callee": "CreateGroupConversationUseCase", "is_member_call": false, "source_file": "C:\\Users\\USERAS\\Desktop\\where\\where-android\\app\\src\\main\\java\\com\\ovi\\where\\di\\UseCaseModule.kt", "source_location": "L144"}, {"caller_nid": "di_usecasemodule_usecasemodule_providesendmessageusecase", "callee": "SendMessageUseCase", "is_member_call": false, "source_file": "C:\\Users\\USERAS\\Desktop\\where\\where-android\\app\\src\\main\\java\\com\\ovi\\where\\di\\UseCaseModule.kt", "source_location": "L145"}, {"caller_nid": "di_usecasemodule_usecasemodule_providesendlocationmessageusecase", "callee": "SendLocationMessageUseCase", "is_member_call": false, "source_file": "C:\\Users\\USERAS\\Desktop\\where\\where-android\\app\\src\\main\\java\\com\\ovi\\where\\di\\UseCaseModule.kt", "source_location": "L146"}, {"caller_nid": "di_usecasemodule_usecasemodule_providemarkconversationreadusecase", "callee": "MarkConversationReadUseCase", "is_member_call": false, "source_file": "C:\\Users\\USERAS\\Desktop\\where\\where-android\\app\\src\\main\\java\\com\\ovi\\where\\di\\UseCaseModule.kt", "source_location": "L147"}, {"caller_nid": "di_usecasemodule_usecasemodule_providefetchlinkpreviewusecase", "callee": "FetchLinkPreviewUseCase", "is_member_call": false, "source_file": "C:\\Users\\USERAS\\Desktop\\where\\where-android\\app\\src\\main\\java\\com\\ovi\\where\\di\\UseCaseModule.kt", "source_location": "L148"}, {"caller_nid": "di_usecasemodule_usecasemodule_providesendvoicemessageusecase", "callee": "SendVoiceMessageUseCase", "is_member_call": false, "source_file": "C:\\Users\\USERAS\\Desktop\\where\\where-android\\app\\src\\main\\java\\com\\ovi\\where\\di\\UseCaseModule.kt", "source_location": "L149"}]}